{"actor":"actress",
  "actors":"actresses",
  "actress":"actor",
  "archduchess":"archduke",
  "archduchesses":"archdukes",
  "archduke":"archduchess",
  "aunt":"uncle",
  "aunts":"uncles",
  "baron":"baroness",
  "baroness":"baron",
  "baronesses":"barons",
  "baronet":"baronetess",
  "baronets":"baronetesses",
  "barons":"baronesses",
  "boy":"girl",
  "boyhood":"girlhood",
  "boyish":"girly",
  "boys":"girls",
  "bro":"sis",
  "bros":"sistas",
  "comte":"comtesse",
  "countess":"count",
  "countesses":"counts",
  "dad":"mom",
  "dads":"moms",
  "deacon":"deaconess",
  "deaconess":"deacon",
  "deaconesses":"deacons",
  "deacons":"deaconesses",
  "duchess":"duke",
  "duchesses":"dukes",
  "dude":"lady",
  "dudelier":"womanlier",
  "dudeliest":"womanliest",
  "dudely":"womanly",
  "dudes":"ladies",
  "duke":"duchess",
  "dukes":"duchesses",
  "earl":"countess",
  "earls":"countesses",
  "emperor":"empress",
  "emperors":"empresses",
  "empress":"emperor",
  "empresses":"emperors",
  "fem":"masc",
  "fiance":"fiancee",
  "fiancee":"fiance",
  "gal":"fellow",
  "gentleman":"lady",
  "gentlemen":"ladies",
  "girl":"boy",
  "girlier":"dudelier",
  "girliest":"dudeliest",
  "girls":"boys",
  "girly":"boyish",
  "god":"goddess",
  "goddess":"god",
  "godhead":"goddesshead",
  "godhood":"goddesshood",
  "godliness":"goddessliness",
  "godly":"goddessly",
  "gramps":"grandma",
  "grandma":"grandpa",
  "grandmas":"grandpas",
  "guy":"gal",
  "guys":"gals",
  "he":"she",
  "hero":"heroine",
  "herself":"himself",
  "himself":"herself",
  "husband":"wife",
  "husbands":"wives",
  "king":"queen",
  "kings":"queens",
  "ladies":"gentlemen",
  "lord":"lady",
  "lords":"ladies",
  "maiden":"stableboy",
  "male":"female",
  "males":"females",
  "mama":"papa",
  "man":"woman",
  "manhood":"womanhood",
  "mankind":"womankind",
  "manliness":"womanliness",
  "manly":"womanly",
  "marquis":"marquise",
  "marquise":"marquise",
  "maternal":"paternal",
  "maternity":"paternity",
  "men":"women",
  "menz":"ladiez",
  "mgtow":"wgtow",
  "mom":"dad",
  "momma":"poppa",
  "moms":"dads",
  "mr":"ms",
  "mrs":"mr",
  "ms":"mr",
  "nephew":"niece",
  "nephews":"nieces",
  "niece":"nephew",
  "nieces":"nephews",
  "papa":"mama",
  "paternal":"maternal",
  "paternity":"maternity",
  "poppa":"momma",
  "priest":"priestess",
  "priestess":"priest",
  "priestesses":"priests",
  "priests":"priestesses",
  "prince":"princess",
  "princes":"princesses",
  "princess":"prince",
  "princesses":"princes",
  "queen":"king",
  "queens":"kings",
  "radfem":"radmasc",
  "she":"he",
  "sir":"ma'am",
  "son":"daughter",
  "sons":"daughters",
  "uncle":"aunt",
  "uncles":"aunts",
  "viscount":"viscountess",
  "viscountess":"viscount",
  "viscountesses":"viscounts",
  "viscounts":"viscountesses",
  "widow":"widower",
  "widower":"widow",
  "wives":"husbands",
  "he'":"she'",
  "ma'am":"sir",
  "she'":"he'",
  "actresses":"actors",
  "bloke":"gal",
  "boyfriend":"girlfriend",
  "bride":"groom",
  "brother":"sister",
  "comtesse":"comte",
  "dame":"knight",
  "damsel":"squire",
  "female":"male",
  "girlfriend":"boyfriend",
  "girlhood":"boyhood",
  "grandpa":"grandma",
  "grandson":"granddaughter",
  "groom":"bride",
  "knight":"dame",
  "lady":"gentleman",
  "maleness":"femaleness",
  "marchioness":"marquess",
  "margrave":"margravine",
  "margravine":"margrave",
  "marquess":"marchioness",
  "matriar":"patriar",
  "matroniz":"patroniz",
  "mother":"father",
  "patriar":"matriar",
  "patroniz":"matroniz",
  "sister":"brother",
  "squire":"damsel",
  "waiter":"waitress",
  "waitress":"waiter",
  "wife":"husband",
  "airman":"airwoman",
  "airmen":"airwomen",
  "alderman":"alderwoman",
  "aldermen":"alderwomen",
  "anchorman":"anchorwoman",
  "anchormen":"anchorwomen",
  "assemblyman":"assemblywoman",
  "assemblymen":"assemblywomen",
  "bogeyman":"bogeywoman",
  "bogeymen":"bogeywomen",
  "bondsman":"bondswoman",
  "bondsmen":"bondswomen",
  "brogrammer":"sistagrammer",
  "bromance":"lady-romance",
  "businessman":"businesswoman",
  "businessmen":"businesswomen",
  "cameraman":"camerawoman",
  "cameramen":"camerawomen",
  "caveman":"cavewoman",
  "cavemen":"cavewomen",
  "chairman":"chairwoman",
  "chairmen":"chairwomen",
  "clergyman":"clergywoman",
  "clergymen":"clergywomen",
  "congressman":"congresswoman",
  "congressmen":"congresswomen",
  "councilman":"councilwoman",
  "councilmen":"councilwomen",
  "countryman":"countrywoman",
  "countrymen":"countrywomen",
  "craftsman":"craftswoman",
  "craftsmen":"craftswomen",
  "d00dz":"laydeez",
  "daddies":"mommies",
  "daddy":"mommy",
  "daughter":"son",
  "doorman":"doorwoman",
  "doormen":"doorwomen",
  "dudebro":"galpal",
  "father":"mother",
  "femin":"mascul",
  "fireman":"firewoman",
  "firemen":"firewomen",
  "fisherman":"fisherwoman",
  "fishermen":"fisherwomen",
  "foreman":"forewoman",
  "foremen":"forewomen",
  "freshman":"freshwoman",
  "freshmen":"freshwomen",
  "garbageman":"garbagewoman",
  "garbagemen":"garbagewomen",
  "godmother":"godfather",
  "grandmother":"grandfather",
  "handyman":"handywoman",
  "handymen":"handywomen",
  "hangman":"hangwoman",
  "hangmen":"hangwomen",
  "henchman":"henchwoman",
  "henchmen":"henchwomen",
  "heroes":"heroines",
  "journeyman":"journeywoman",
  "journeymen":"journeywomen",
  "kinsman":"kinswoman",
  "kinsmen":"kinswomen",
  "klansman":"klanswoman",
  "ladiez":"menz",
  "laydeez":"d00dz",
  "layman":"laywoman",
  "laymen":"laywomen",
  "madman":"madwoman",
  "madmen":"madwomen",
  "mailman":"mailwoman",
  "mailmen":"mailwomen",
  "mansplain":"ladysplain",
  "marksman":"markswoman",
  "marksmen":"markswomen",
  "mascul":"femin",
  "middleman":"middlewoman",
  "middlemen":"middlewomen",
  "milkman":"milkwoman",
  "milkmen":"milkwomen",
  "misandr":"misogyn",
  "misogyn":"misandr",
  "mommies":"daddies",
  "mommy":"daddy",
  "nobleman":"noblewoman",
  "noblemen":"noblewomen",
  "ombudsman":"ombudswoman",
  "ombudsmen":"ombudswomen",
  "policeman":"policewoman",
  "policemen":"policewomen",
  "postman":"postwoman",
  "postmen":"postwomen",
  "repairman":"repairwoman",
  "repairmen":"repairwomen",
  "salesman":"saleswoman",
  "salesmen":"saleswomen",
  "sandman":"sandwoman",
  "sandmen":"sandwomen",
  "serviceman":"servicewoman",
  "servicemen":"servicewomen",
  "showman":"showwoman",
  "showmen":"showwomen",
  "snowman":"snowwoman",
  "sorostitute":"bro-whore",
  "spaceman":"spacewoman",
  "spacemen":"spacewomen",
  "spokesman":"spokeswoman",
  "spokesmen":"spokeswomen",
  "sportsman":"sportswoman",
  "sportsmen":"sportswomen",
  "statesman":"stateswoman",
  "statesmen":"stateswomen",
  "stepbrother":"stepsister",
  "stepmother":"stepfather",
  "stepsister":"stepbrother",
  "superman":"superwoman",
  "supermen":"superwomen",
  "unman":"unwoman",
  "watchman":"watchwoman",
  "watchmen":"watchwomen",
  "weatherman":"weatherwoman",
  "weathermen":"weatherwomen",
  "whitemaleness":"whitefemaleness",
  "woman":"man",
  "women":"men",
  "workman":"workwoman",
  "workmen":"workwomen",
  "heroine":"hero",
  "heroines":"heroes"
}



